.gitignore
AUTHORS
LICENSE
README.md
setup.py
wallaby/__init__.py
wallaby/pf/__init__.py
wallaby/pf/peer/__init__.py
wallaby/pf/peer/couchDB.py
wallaby/plugins/__init__.py
wallaby/plugins/couchdb/__init__.py
wallaby/plugins/couchdb/document.py
wallaby_plugin_couchdb.egg-info/PKG-INFO
wallaby_plugin_couchdb.egg-info/SOURCES.txt
wallaby_plugin_couchdb.egg-info/dependency_links.txt
wallaby_plugin_couchdb.egg-info/requires.txt
wallaby_plugin_couchdb.egg-info/top_level.txt