Metadata-Version: 1.1
Name: wallaby-plugin-couchdb
Version: 0.1.9
Summary: This package integrates the couchdb backend into wallaby.
Home-page: http://freshx.de/wallaby/plugins/couchdb
Author: FreshX GbR
Author-email: wallaby@freshx.de
License: BSD
Platform: UNKNOWN
Classifier: Development Status :: 4 - Beta
Classifier: Framework :: Twisted
Classifier: Intended Audience :: Developers
Classifier: Intended Audience :: System Administrators
Classifier: License :: OSI Approved :: BSD License
Classifier: Operating System :: MacOS :: MacOS X
Classifier: Operating System :: Microsoft :: Windows
Classifier: Operating System :: POSIX :: Linux
Classifier: Programming Language :: Python :: 2.7
Classifier: Topic :: Software Development :: Libraries :: Application Frameworks
